ldapter/__init__.py
ldapter/cache.py
ldapter/dict_cache.py
ldapter/directory.py
ldapter/inet_org_person.py
ldapter/ldap_provider.py
ldapter/openldap_provider.py
ldapter/redis_cache.py
ldapter/schema.py
ldapter/scope.py
ldapter-0.0.10.dist-info/LICENSE
ldapter-0.0.10.dist-info/METADATA
ldapter-0.0.10.dist-info/WHEEL
ldapter-0.0.10.dist-info/top_level.txt
ldapter-0.0.10.dist-info/RECORD
