Metadata-Version: 2.1
Name: ldapter
Version: 0.0.10
Summary: A lightweight adapter API for python-ldap with read-through caching to Redis
Home-page: https://code.vt.edu/crest/ldapter
Author: Carl Harris
Author-email: ceharris414@gmail.com
License: UNKNOWN
Project-URL: Bug Tracker, https://code.vt.edu/crest/ldapter/-/issues
Platform: UNKNOWN
Classifier: Programming Language :: Python :: 3
Classifier: License :: OSI Approved :: MIT License
Classifier: Operating System :: OS Independent
Requires-Python: >=3.8
License-File: LICENSE
Requires-Dist: python-ldap
Requires-Dist: python-dateutil
Requires-Dist: redis
